django_test_curl/__init__.py
django_test_curl/django_test_curl.py
django_test_curl/test_django_test_curl.py
django_test_curl-0.2.0.dist-info/LICENSE
django_test_curl-0.2.0.dist-info/WHEEL
django_test_curl-0.2.0.dist-info/METADATA
django_test_curl-0.2.0.dist-info/RECORD
