Metadata-Version: 2.1
Name: django-test-curl
Version: 0.2.0
Summary: Write Django test requests using curl syntax
Home-page: https://github.com/crccheck/django-test-curl
License: Apache-2.0
Keywords: django,curl,tests
Author: crccheck
Author-email: oss@crccheck.com
Requires-Python: >=3.6.2,<4.0.0
Classifier: Development Status :: 4 - Beta
Classifier: Framework :: Django
Classifier: License :: OSI Approved :: Apache Software License
Classifier: Programming Language :: Python :: 3
Classifier: Programming Language :: Python :: 3.10
Classifier: Programming Language :: Python :: 3.7
Classifier: Programming Language :: Python :: 3.8
Classifier: Programming Language :: Python :: 3.9
Classifier: Topic :: Software Development :: Testing
Project-URL: Repository, https://github.com/crccheck/django-test-curl
